pycallblock/__init__.py
pycallblock/modem.py
pycallblock/shielded_codes_to_dte.json
pycallblock/util.py
pycallblock-1.1.0.dist-info/LICENSE
pycallblock-1.1.0.dist-info/METADATA
pycallblock-1.1.0.dist-info/WHEEL
pycallblock-1.1.0.dist-info/entry_points.txt
pycallblock-1.1.0.dist-info/top_level.txt
pycallblock-1.1.0.dist-info/RECORD
