Metadata-Version: 2.1
Name: pycallblock
Version: 1.1.0
Summary: Block spam calls with a USB modem.
Author-email: AT0myks <at0myks.dev@gmail.com>
Project-URL: Issues, https://github.com/AT0myks/pycallblock/issues
Project-URL: Source, https://github.com/AT0myks/pycallblock
Keywords: modem,block,spam,phone,call
Classifier: Development Status :: 5 - Production/Stable
Classifier: Framework :: AsyncIO
Classifier: Intended Audience :: Developers
Classifier: Intended Audience :: End Users/Desktop
Classifier: License :: OSI Approved :: GNU General Public License v3 (GPLv3)
Classifier: Operating System :: POSIX :: Linux
Classifier: Programming Language :: Python :: 3
Classifier: Programming Language :: Python :: 3 :: Only
Classifier: Programming Language :: Python :: 3.9
Classifier: Programming Language :: Python :: 3.10
Classifier: Programming Language :: Python :: 3.11
Classifier: Topic :: Communications
Classifier: Topic :: Communications :: Fax
Classifier: Topic :: Communications :: Telephony
Classifier: Topic :: Software Development :: Libraries
Classifier: Topic :: Software Development :: Libraries :: Python Modules
Classifier: Topic :: Multimedia :: Sound/Audio :: Capture/Recording
Requires-Python: >=3.9
License-File: LICENSE
Requires-Dist: pyserial-asyncio
